README.md
setup.py
f1chexbert/__init__.py
f1chexbert/f1chexbert.py
f1chexbert.egg-info/PKG-INFO
f1chexbert.egg-info/SOURCES.txt
f1chexbert.egg-info/dependency_links.txt
f1chexbert.egg-info/not-zip-safe
f1chexbert.egg-info/requires.txt
f1chexbert.egg-info/top_level.txt
tests/__init__.py
tests/f1chexbert_test.py