Metadata-Version: 2.1
Name: f1chexbert
Version: 0.0.2
Summary: UNKNOWN
Author: Jean-Benoit Delbrouck
License: MIT
Platform: UNKNOWN
Classifier: Intended Audience :: Science/Research
Classifier: Topic :: Scientific/Engineering
Classifier: License :: OSI Approved :: MIT License
Classifier: Programming Language :: Python :: 3 :: Only
Requires-Python: >=3.8
